{
  "projectApplicationId": 414,
  "requirementId": 898,
  "files": [
    "frontend/src/pages/page.tsx"
  ],
  "activityMeta": [
    {
      "file": "frontend/src/pages/page.tsx",
      "requirementId": 898,
      "requirementName": "Define portfolio layout",
      "changes": 1,
      "modifiedRanges": [
        {
          "startLine": 3,
          "endLine": 3,
          "lineCount": 1
        },
        {
          "startLine": 5,
          "endLine": 14,
          "lineCount": 10
        },
        {
          "startLine": 18,
          "endLine": 23,
          "lineCount": 6
        },
        {
          "startLine": 37,
          "endLine": 40,
          "lineCount": 4
        },
        {
          "startLine": 44,
          "endLine": 45,
          "lineCount": 2
        },
        {
          "startLine": 47,
          "endLine": 47,
          "lineCount": 1
        },
        {
          "startLine": 49,
          "endLine": 49,
          "lineCount": 1
        }
      ],
      "timestamps": {
        "firstModified": "2026-06-20T08:32:18.362Z",
        "lastModified": "2026-06-20T08:32:18.362Z"
      },
      "activity": {
        "activeDurationSec": 0,
        "idleBreaks": 0,
        "avgIntervalSec": 0
      },
      "diffStats": {
        "linesAdded": 34,
        "linesDeleted": 56,
        "largeChangeEvents": 0
      },
      "patterns": {
        "burstEdits": false,
        "longPauseBeforeEdit": false
      },
      "sourceHints": {
        "possiblePaste": false,
        "suspiciousJump": false
      }
    }
  ]
}
